task_3/__init__.py
task_3/__main__.py
task_3_something_something-0.1.0.dist-info/METADATA
task_3_something_something-0.1.0.dist-info/WHEEL
task_3_something_something-0.1.0.dist-info/top_level.txt
task_3_something_something-0.1.0.dist-info/RECORD
